sandboxer/__init__.py
sandboxer/cli.py
sandboxer/container.py
sandboxer-0.1.5.dist-info/METADATA
sandboxer-0.1.5.dist-info/WHEEL
sandboxer-0.1.5.dist-info/entry_points.txt
sandboxer-0.1.5.dist-info/licenses/LICENSE
sandboxer-0.1.5.dist-info/RECORD
