Metadata-Version: 2.4
Name: sandboxer
Version: 0.1.5
Summary: A CLI tool for sandboxing folders into containers with Claude Code support
License-File: LICENSE
Requires-Python: >=3.12
Requires-Dist: rich>=13.0.0
Requires-Dist: typer>=0.12.0
Provides-Extra: dev
Requires-Dist: pytest>=8.0.0; extra == 'dev'
